ai_agent_cli/__init__.py
ai_agent_cli/cli.py
ai_agent_cli/core/__init__.py
ai_agent_cli/core/agent.py
ai_agent_cli/core/ai_provider.py
ai_agent_cli/core/config.py
ai_agent_cli/core/file_manager.py
ai_agent_cli/core/prompt_engine.py
ai_agent_cli/core/shell_runner.py
open_agent_cli-1.0.0.dist-info/METADATA
open_agent_cli-1.0.0.dist-info/WHEEL
open_agent_cli-1.0.0.dist-info/entry_points.txt
open_agent_cli-1.0.0.dist-info/top_level.txt
open_agent_cli-1.0.0.dist-info/RECORD
