Metadata-Version: 2.4
Name: open-agent-cli
Version: 1.0.0
Summary: 🤖 CLI de IA para desenvolvimento - Cria projetos estruturados e código limpo usando OpenAI ou Google Gemini
Author-email: Gustavo <gustavdesousalima@gmail.com>
Maintainer-email: Gustavo <gustavdesousalima@gmail.com>
License-Expression: MIT
Project-URL: Homepage, https://github.com/gustavodesousalima/open-agent-cli
Project-URL: Documentation, https://github.com/gustavodesousalima/open-agent-cli#readme
Project-URL: Repository, https://github.com/gustavodesousalima/open-agent-cli
Project-URL: Bug Tracker, https://github.com/gustavodesousalima/open-agent-cli/issues
Keywords: ai,cli,development,code-generation,openai,gemini,clean-code
Classifier: Development Status :: 4 - Beta
Classifier: Intended Audience :: Developers
Classifier: Operating System :: OS Independent
Classifier: Programming Language :: Python :: 3
Classifier: Programming Language :: Python :: 3.10
Classifier: Programming Language :: Python :: 3.11
Classifier: Programming Language :: Python :: 3.12
Classifier: Topic :: Software Development :: Libraries :: Python Modules
Classifier: Topic :: Software Development :: Code Generators
Classifier: Topic :: Software Development :: Quality Assurance
Classifier: Topic :: Utilities
Requires-Python: >=3.10
Requires-Dist: rich>=13.0.0
Requires-Dist: click>=8.0.0
Requires-Dist: pydantic>=2.0.0
Requires-Dist: openai>=1.0.0
Requires-Dist: google-generativeai>=0.3.0
Requires-Dist: autopep8>=2.0.0
